Workbook

Sheet Resumen
A1: FINANZAS DEL PROYECTO
A2: Esta hoja se calcula sola. Cargá datos en las pestañas 'Rifa del Peso', 'Remeras' y 'Gastos'.
A4: INGRESOS
A5: Rifa del peso | B5: ='Rifa del Peso'!G4 -> 25000
A6: Remeras (recaudo) | B6: =Remeras!H5 -> 1470
A7: Remeras vendidas (unidades) | B7: =Remeras!H4 -> 3
A8: TOTAL INGRESOS | B8: =B5+B6 -> 26470
A10: GASTOS
A11: Maquillaje | B11: =Gastos!G5 -> 12000
A12: Luces | B12: =Gastos!G6 -> 0
A13: Escenografía | B13: =Gastos!G7 -> 0
A14: Utilería | B14: =Gastos!G8 -> 0
A15: Vestuario | B15: =Gastos!G9 -> 0
A16: Audio | B16: =Gastos!G10 -> 0
A17: Comida | B17: =Gastos!G11 -> 0
A18: TOTAL GASTOS | B18: =SUM(B11:B17) -> 12000
A20: RESULTADO
A21: SALDO (Ingresos − Gastos) | B21: =B8-B18 -> 14470

Sheet Rifa del Peso
A1: RIFA DEL PESO
A2: Celdas rosas = para completar. Una fila por recaudo; elegí el componente del menú. La fila 5 es un ejemplo: reemplazala.
A4: Fecha | B4: Componente | C4: Detalle | D4: Monto recaudado | F4: TOTAL RIFA | G4: =SUM(D5:D204) -> 25000
A5: 46310 | B5: Cami | C5: Ejemplo: recaudo rifa del peso | D5: 25000

Sheet Remeras
A1: VENTA DE REMERAS
A2: Celdas rosas = para completar. Una fila por venta; elegí el componente y poné las unidades. El recaudo se calcula solo con el precio por unidad. La fila 5 es un ejemplo: reemplazala.
A4: Fecha | B4: Componente | C4: Detalle (talle, comprador, etc.) | D4: Cantidad (unidades) | E4: Recaudo | G4: TOTAL UNIDADES | H4: =SUM(D5:D204) -> 3
A5: 46315 | B5: Luci | C5: Ejemplo: 3 remeras talle M | D5: 3 | E5: =IF(D5="","",D5*$H$6) -> 1470 | G5: TOTAL RECAUDO | H5: =SUM(E5:E204) -> 1470
E6: =IF(D6="","",D6*$H$6) | G6: Precio por unidad | H6: 490
E7: =IF(D7="","",D7*$H$6)
E8: =IF(D8="","",D8*$H$6)
E9: =IF(D9="","",D9*$H$6)
E10: =IF(D10="","",D10*$H$6)
E11: =IF(D11="","",D11*$H$6)
E12: =IF(D12="","",D12*$H$6)
E13: =IF(D13="","",D13*$H$6)
E14: =IF(D14="","",D14*$H$6)
E15: =IF(D15="","",D15*$H$6)
E16: =IF(D16="","",D16*$H$6)
E17: =IF(D17="","",D17*$H$6)
E18: =IF(D18="","",D18*$H$6)
... E204: =IF(D204="","",D204*$H$6)

Sheet Gastos
A1: GASTOS
A2: Celdas rosas = para completar. Elegí la categoría del menú desplegable. La fila 5 es un ejemplo: reemplazala.
A4: Fecha | B4: Categoría | C4: Detalle | D4: Monto | F4: Categoría | G4: Total
A5: 46317 | B5: Maquillaje | C5: Ejemplo: bases y pinceles | D5: 12000 | F5: Maquillaje | G5: =SUMIF($B$5:$B$204,F5,$D$5:$D$204) -> 12000
F6: Luces | G6: =SUMIF($B$5:$B$204,F6,$D$5:$D$204) -> 0
F7: Escenografía | G7: =SUMIF($B$5:$B$204,F7,$D$5:$D$204) -> 0
F8: Utilería | G8: =SUMIF($B$5:$B$204,F8,$D$5:$D$204) -> 0
F9: Vestuario | G9: =SUMIF($B$5:$B$204,F9,$D$5:$D$204) -> 0
F10: Audio | G10: =SUMIF($B$5:$B$204,F10,$D$5:$D$204) -> 0
F11: Comida | G11: =SUMIF($B$5:$B$204,F11,$D$5:$D$204) -> 0
F12: TOTAL GASTOS | G12: =SUM(G5:G11) -> 12000
